MANIFEST.in
readme.md
setup.py
hello/__init__.py
vasalksyy_package.egg-info/PKG-INFO
vasalksyy_package.egg-info/SOURCES.txt
vasalksyy_package.egg-info/dependency_links.txt
vasalksyy_package.egg-info/top_level.txt