Metadata-Version: 1.0
Name: vasalksyy-package
Version: 0.1.5
Summary: Hello world package
Home-page: UNKNOWN
Author: vasalskyy
Author-email: vasalskyyy@gmail.com
License: UNKNOWN
Platform: UNKNOWN
